amdsharktuner/__init__.py
amdsharktuner/candidate_gen.py
amdsharktuner/candidate_ordering.py
amdsharktuner/common.py
amdsharktuner/constraint_generator.py
amdsharktuner/dispatch_constraints.py
amdsharktuner/dispatch_parser.py
amdsharktuner/libtuner.py
amdsharktuner/merge_td_specs.py
amdsharktuner/process_utils.py
amdsharktuner/py.typed
amdsharktuner/spec_builder.py
amdsharktuner/test_utils.py
boo_tuner/__init__.py
boo_tuner/__main__.py
boo_tuner/boo_tuner.py
dispatch_tuner/__init__.py
dispatch_tuner/__main__.py
dispatch_tuner/dispatch_tuner.py
model_tuner/__init__.py
model_tuner/__main__.py
model_tuner/model_tuner.py
amdsharktuner-3.9.0.dist-info/METADATA
amdsharktuner-3.9.0.dist-info/WHEEL
amdsharktuner-3.9.0.dist-info/top_level.txt
amdsharktuner-3.9.0.dist-info/RECORD
