Metadata-Version: 2.4
Name: amdsharktuner
Version: 3.9.0
Summary: IREE Model and Dispatch Tuner
Author: amdshark Authors
License-Expression: Apache-2.0
Project-URL: Repository, https://github.com/nod-ai/amd-shark-ai
Classifier: Development Status :: 3 - Alpha
Classifier: Programming Language :: Python :: 3
Classifier: Programming Language :: Python :: 3.10
Classifier: Programming Language :: Python :: 3.11
Classifier: Programming Language :: Python :: 3.12
Classifier: Programming Language :: Python :: 3.13
Requires-Python: >=3.10
Requires-Dist: iree-base-compiler
Requires-Dist: iree-base-runtime
Requires-Dist: numpy
Requires-Dist: PyYAML
Requires-Dist: typing_extensions
Requires-Dist: tqdm>=4.66.4
Requires-Dist: z3_solver>=4.13.0.0
Provides-Extra: dev
Requires-Dist: mypy==1.8.0; extra == "dev"
Requires-Dist: pre-commit==3.8.0; extra == "dev"
Requires-Dist: virtualenv==20.26.6; extra == "dev"
Requires-Dist: types-setuptools>=80.9.0.20250822; extra == "dev"
Requires-Dist: types-tqdm>=4.66.0.20240417; extra == "dev"
